[
  {
    "name": "bitcoin",
    "displayName": "Wrapped Bitcoin",
    "symbol": "WBTC"
  },
  {
    "name": "usd-coin",
    "displayName": "USD Coin",
    "symbol": "USDC"
  },
  {
    "name": "uniswap",
    "displayName": "Uniswap",
    "symbol": "UNI"
  },
  {
    "name": "chainlink",
    "displayName": "Chainlink",
    "symbol": "LINK"
  },
  {
    "name": "synthetix",
    "displayName": "Synthetix Network",
    "symbol": "SNX"
  },
  {
    "name": "fantom",
    "displayName": "Fantom",
    "symbol": "FTM"
  },
  {
    "name": "aave",
    "displayName": "Aave",
    "symbol": "AAVE"
  },
  {
    "name": "compound",
    "displayName": "Compound",
    "symbol": "COMP"
  },
  {
    "name": "sushi",
    "displayName": "Sushi",
    "symbol": "SUSHI"
  },
  {
    "name": "yearn",
    "displayName": "Yearn Finance",
    "symbol": "YFI"
  }
]
